dtactions/README.md
dtactions/__init__.py
dtactions/autohotkeyactions.py
dtactions/messagefunctions.py
dtactions/monitorfunctions.py
dtactions/natlinkclipboard.py
dtactions/scintillacon.py
dtactions/sendkeys.py
dtactions/samples/autohotkey/getintoforeground.ahk
dtactions/samples/autohotkey/showmessageswindow.ahk
dtactions/samples/unimacro/unimacroactions.ini
dtactions/unimacro/ding.wav
dtactions/unimacro/extenvvars.py
dtactions/unimacro/inivars.py
dtactions/unimacro/newactions.py
dtactions/unimacro/unimacroactions.py
dtactions/unimacro/unimacroutils.py
dtactions/unimacro/usc_functions.py
dtactions/unimacro/utilsqh.py
dtactions/unimacro/actionclasses/__init__.py
dtactions/unimacro/actionclasses/actionbases.py
dtactions/unimacro/actionclasses/code-actions.py
dtactions/unimacro/actionclasses/excel-actions.py
dtactions/unimacro/actionclasses/frescobaldi-actions.py
dtactions/unimacro/actionclasses/komodo-actions.py
dtactions/unimacro/actionclasses/notreadykomodo-actions.py
dtactions/unimacro/actionclasses/pythonwin-actions.py
dtactions/unimacro/actionclasses/uedit32-actions.py
dtactions/unimacro/actionclasses/uedit64-actions.py
dtactions/unimacro/actionclasses/win32pad-actions.py
dtactions/vocola_compatibility/README.txt
dtactions/vocola_compatibility/Unimacro.vch
dtactions/vocola_compatibility/_Unimacro_regression.vcl
dtactions/vocola_sendkeys/ExtendedSendDragonKeys.py
dtactions/vocola_sendkeys/SendInput.py
dtactions/vocola_sendkeys/ext_keys.py
dtactions-1.6.3.dist-info/entry_points.txt
dtactions-1.6.3.dist-info/WHEEL
dtactions-1.6.3.dist-info/METADATA
dtactions-1.6.3.dist-info/RECORD
