Metadata-Version: 2.1
Name: dtactions
Version: 1.6.3
Summary: dtactions __init__
Keywords: dragon,speech,dictation,dictation-toolbox,natlink
Author-email: Quintijn Hoogenboom <q.hoogenboom@antenna.nl>
Maintainer-email: Quintijn Hoogenboom <q.hoogenboom@antenna.nl>, LexiconCode <CasterVoice@protonmail.com>
Requires-Python: >=3.9
Classifier: Development Status :: 4 - Beta
Classifier: Topic :: Multimedia :: Sound/Audio :: Speech
Classifier: Topic :: Scientific/Engineering :: Human Machine Interfaces
Requires-Dist: pywin32 >= 300
Requires-Dist: debugpy
Requires-Dist: platformdirs
Requires-Dist: pyenvutils ; extra == "dev"
Requires-Dist: build ; extra == "dev"
Requires-Dist: pytest >=7.1.2 ; extra == "test"
Project-URL: Home, https://github.com/dictation-toolbox/dtactions
Project-URL: Readthedocs, https://dtactions.readthedocs.io/en/latest/sendkeys.html
Provides-Extra: dev
Provides-Extra: test
